{
  "rsvpDescription": [
    "본인과 본인의 손님 참석여부를 꼭 확인해 주세요",
    "Please RSVP for you and your guest"
  ],
  "rsvpTotal": ["본인 포함한 참석인원", "Total Attending Including Yourself"],
  "rsvpInvited": ["초대", "Invited"],
  "rsvpSubmit": ["참석합니다", "RSVP"],
  "rsvpCancel": ["참석 못합니다", "Cancle RSVP"],
  "rsvpUninvited": [
    "초대받지 못한 손님과\n동반하고 싶으시면 꼭 연락해주세요",
    "If you wish to bring uninvited guests,\nplease let us know asap."
  ],

  "direction": ["찾아오시는길", "Get Direction"],
  "blessing": ["마음 전하실곳", "Send Blessings"],
  "blessingSucess": [
    "축복 감사합니다. 행복하게 살겠습니다!",
    "Thank you for your blessing!"
  ],
  "bujo": [
    "더욱 격렬하게 축복하고 싶으시다고요?",
    "Want to get the couple something extra?"
  ],
  "bujoThanks": ["감사합니다!", "Thank you so much!"],

  "submit": ["보내기", "Submit"],
  "expand": ["자세히", "Expand"],
  "scrollDown": ["자세히", "Scroll Down"],
  "contact": ["Contact", "Contact"],
  "nameGroom": ["한정훈", "Junghoon Han"],
  "nameGroomF": ["한현구", "Hyungoo Han"],
  "nameGroomM": ["강무환", "Mohwan Kang"],
  "nameBride": ["김예원", "Yeweon Kim"],
  "nameBrideF": ["김정수", "Jeongsoo Kim"],
  "nameBrideM": ["정정희", "Jeonghee Jeong"]
}
